{
  "type" : "HTTP",
  "vendor" : "Citrix",
  "id" : "d0e9e55e-016b-4023-a475-fad607236dad",
  "trackingUuid" : "65a95fb8-6163-481e-b485-fd1d7ea5cdbb",
  "title" : "Cherwell",
  "description" : "Integrate with Cherwell for employees to submit and monitor incident, service requests, and take action through Microapps. It also provides microapps for  higher tier agents the ability to review incidents. ",
  "iconUrl" : "https://iws-prod-global-customicons-cdn-endpoint.azureedge.net/image/CVBBEObHKTf9fk8XR5nIHwIlAZuY1YWd.png",
  "masVersion" : "1.111.0.01692c96774764c200e9cb1d75887f4ff71bd8c5",
  "categories" : [ "WEB_SERVICES" ],
  "created" : "2021-09-03T13:53:34",
  "supportsOAuthForActions" : false,
  "i18nLanguages" : [ "en" ],
  "apps" : [ {
    "uuid" : "25f8dbb0-3c99-4a86-9b06-81ed289237eb",
    "trackingUuid" : "26d6e7a1-c033-4b16-b94b-baa6b209753c",
    "title" : "Create Service Request",
    "numberOfEvents" : 0,
    "action" : true
  }, {
    "uuid" : "38a6ce45-de39-45e8-8e5f-e87189a0f2b9",
    "trackingUuid" : "a974eae3-50de-45cf-a248-7c1b837fa527",
    "title" : "My Open Incidents",
    "numberOfEvents" : 4,
    "action" : true
  }, {
    "uuid" : "571f7cf8-b7b9-4579-affd-4c734cf570b6",
    "trackingUuid" : "a857830e-9cf6-4f08-8f6b-b45bef14c917",
    "title" : "My Open Service Requests",
    "numberOfEvents" : 4,
    "action" : true
  }, {
    "uuid" : "7ec3a74f-a340-4bb9-9994-b3eb6290bf96",
    "trackingUuid" : "67d63cff-d47e-4212-80c2-0b71b2d4ad5e",
    "title" : "Create Incident",
    "numberOfEvents" : 0,
    "action" : true
  } ],
  "vaResolvers" : [ ],
  "tags" : [ {
    "tag" : "helpUrl",
    "value" : " https://docs.citrix.com/en-us/citrix-microapps/set-up-template-integrations/integrate-cherwell.html "
  } ],
  "scriptMetadata" : {
    "originalFileName" : "Cherwell.js",
    "storedFileName" : "Cherwell.js",
    "checksum" : "D9075E5B15812CFDFB6A83A79EEE1515",
    "apiVersion" : "1.1"
  },
  "hideAddButton" : false
}