{
  "type" : "DIP",
  "vendor" : "Citrix",
  "id" : "com.sapho.services.workday.WorkdayService",
  "trackingUuid" : "22435482-9b80-4831-a026-1ff824c7704d",
  "version" : "0.1.16",
  "title" : "Workday",
  "description" : "Test change 3.",
  "iconUrl" : "https://ctx-ws-cdn.cloud.com/assets/microapps/exported/Workday.53a6fa429a68457228ca68adf0c387e6.svg",
  "masVersion" : "1.51.0-SNAPSHOT",
  "categories" : [ "LEGACY" ],
  "created" : "2021-01-07T12:12:23",
  "deprecatedDate": "2021-08-01T00:00:00Z",
  "eolDateWithSupport": "2021-11-01T00:00:00Z",
  "supportsOAuthForActions" : true,
  "i18nLanguages" : [ "de", "en", "es", "fr", "it", "ja", "nl", "pt-BR", "zh-CN" ],
  "apps" : [ {
    "uuid" : "2e2d33c6-d59f-4be4-9d8e-85cbd952e9ea",
    "trackingUuid" : "c26ac5a8-efc8-4de1-bc30-570b09fe46f1",
    "title" : "PTO Balance",
    "numberOfEvents" : 0,
    "action" : false
  }, {
    "uuid" : "33ec2632-c49c-4b17-b107-feea3a286d66",
    "trackingUuid" : "5742ec6a-a067-4b33-8538-76e9b9b6663f",
    "title" : "Create PTO Request",
    "numberOfEvents" : 0,
    "action" : true
  }, {
    "uuid" : "37f53417-5e33-404c-bd9d-8a4d47b25a61",
    "trackingUuid" : "c5074fc6-5ca5-400d-84e6-e1ac3d7e0d33",
    "title" : "PTO Requests",
    "numberOfEvents" : 1,
    "action" : true
  }, {
    "uuid" : "39e32183-4129-407e-aa08-0eeee410b29c",
    "trackingUuid" : "9c8b0b4a-9878-4cd3-8151-f62de1c22035",
    "title" : "Create Expense Report",
    "numberOfEvents" : 0,
    "action" : true
  }, {
    "uuid" : "3e5342cd-c789-424b-ad01-d64d5dc42359",
    "trackingUuid" : "ddf1c30b-5490-4a82-b237-37a081f8d3a0",
    "title" : "My Purchase Orders",
    "numberOfEvents" : 0,
    "action" : true
  }, {
    "uuid" : "54eaa841-ae81-49aa-8676-6a93dbe3dc16",
    "trackingUuid" : "da7eb212-112f-4303-a7ed-2d141f935c66",
    "title" : "Change Job Requests",
    "numberOfEvents" : 1,
    "action" : true
  }, {
    "uuid" : "5defde70-1870-47c1-9665-3c465580f666",
    "trackingUuid" : "3f70a358-3d89-4cf2-886d-e33cb8a58044",
    "title" : "My PTO Requests",
    "numberOfEvents" : 1,
    "action" : true
  }, {
    "uuid" : "8eb46a19-7868-4bb1-861b-09acedcb80a0",
    "trackingUuid" : "188d6f3a-b48f-492d-b326-90a22cb0ef29",
    "title" : "Create Milestone",
    "numberOfEvents" : 0,
    "action" : true
  }, {
    "uuid" : "a9bb9cd2-eddc-40c0-afbd-587b83185811",
    "trackingUuid" : "0a1e2aac-3c28-4a5a-bfd8-e59f128f65ab",
    "title" : "Create Change Job",
    "numberOfEvents" : 0,
    "action" : true
  }, {
    "uuid" : "b599aa6c-4671-4a8c-b304-f87fa1ef7035",
    "trackingUuid" : "f7bf60e3-6cf4-49c4-8f02-827869ec6c16",
    "title" : "Expense Reports",
    "numberOfEvents" : 1,
    "action" : true
  }, {
    "uuid" : "f59df54b-f949-4585-ad7e-4c73c1b4a504",
    "trackingUuid" : "f7afc86e-c67b-428c-badc-0fa1ab839b4c",
    "title" : "Milestones",
    "numberOfEvents" : 1,
    "action" : true
  }, {
    "uuid" : "ff339904-b484-4b3e-815e-720041de8aae",
    "trackingUuid" : "cfd6ad44-9817-49c0-a940-997a944ea5c1",
    "title" : "My Expenses",
    "numberOfEvents" : 1,
    "action" : true
  } ],
  "vaResolvers" : [ {
      "name" : "Directory Details",
      "intentName" : "Directory.Details"
    }, {
      "name" : "Directory Lookup",
      "intentName" : "Directory.Lookup"
    }, {
      "name" : "Directory Question Address",
      "intentName" : "Directory.Question.Address"
    }, {
      "name" : "Directory Question Email",
      "intentName" : "Directory.Question.Email"
    }, {
      "name" : "Directory Question Location",
      "intentName" : "Directory.Question.Location"
    }, {
      "name" : "Directory Question Manager",
      "intentName" : "Directory.Question.Manager"
    }, {
      "name" : "Directory Question Phone",
      "intentName" : "Directory.Question.Phone"
    }, {
      "name" : "Directory Question Position",
      "intentName" : "Directory.Question.Position"
    } ],
    "tags" : [ {
      "tag" : "helpUrl",
      "value" : "https://docs.citrix.com/en-us/citrix-microapps/set-up-template-integrations/integrate-workday.html"
    } ]
  }
